splendsp/__init__.py
splendsp/_version.py
splendsp/cut/__init__.py
splendsp/cut/_cut.py
splendsp/cut/_utils.py
splendsp/dsp/__init__.py
splendsp/dsp/_de_pileup.py
splendsp/dsp/_fitting.py
splendsp/dsp/_noise.py
splendsp/dsp/_of_pileup.py
splendsp/dsp/_utils.py
splendsp/plot/__init__.py
splendsp/plot/_plot.py
splendsp-0.2.7.dist-info/licenses/LICENSE
splendsp-0.2.7.dist-info/METADATA
splendsp-0.2.7.dist-info/WHEEL
splendsp-0.2.7.dist-info/top_level.txt
splendsp-0.2.7.dist-info/RECORD
