Metadata-Version: 2.4
Name: splendsp
Version: 0.2.7
Summary: Splendid Digital Signal Processing of time series data for small physics experiments
Home-page: https://github.com/splendor-collab/splendsp
Author: SPLENDOR Collaboration
Maintainer: SPLENDOR collaboration
License: MIT
Requires-Python: >=3.6
License-File: LICENSE
Requires-Dist: numpy
Requires-Dist: scipy
Requires-Dist: matplotlib
Requires-Dist: seaborn
Requires-Dist: astropy
Dynamic: license-file
